MANIFEST.in
digest.json
package.json
setup.py
dash_renderer/__init__.py
dash_renderer/dash_renderer.dev.js
dash_renderer/dash_renderer.min.js
dash_renderer/polyfill@7.8.7.min.js
dash_renderer/prop-types@15.7.2.js
dash_renderer/prop-types@15.7.2.min.js
dash_renderer/react-dom@16.14.0.js
dash_renderer/react-dom@16.14.0.min.js
dash_renderer/react@16.14.0.js
dash_renderer/react@16.14.0.min.js
dash_renderer.egg-info/PKG-INFO
dash_renderer.egg-info/SOURCES.txt
dash_renderer.egg-info/dependency_links.txt
dash_renderer.egg-info/top_level.txt