Metadata-Version: 1.0
Name: dash_renderer
Version: 1.9.1
Summary: Front-end component renderer for Dash
Home-page: UNKNOWN
Author: Chris Parmer
Author-email: chris@plotly.com
License: MIT
Platform: UNKNOWN
